{
  "project_info": {
    "project_number": "601697725144",
    "firebase_url": "https://bsmart-22c4d.firebaseio.com",
    "project_id": "bsmart-22c4d",
    "storage_bucket": "bsmart-22c4d.appspot.com"
  },
  "client": [
    {
      "client_info": {
        "mobilesdk_app_id": "1:601697725144:android:40e014910f015c39",
        "android_client_info": {
          "package_name": "th.co.mistine.faceso"
        }
      },
      "oauth_client": [
        {
          "client_id": "601697725144-g2u8mpad3t2j2i74hg2icp1l0mhrn1sc.apps.googleusercontent.com",
          "client_type": 3
        }
      ],
      "api_key": [
        {
          "current_key": "AIzaSyCPIUl6v9gVZtUAlDfPByv7pFZJS66i9SI"
        }
      ],
      "services": {
        "analytics_service": {
          "status": 1
        },
        "appinvite_service": {
          "status": 1,
          "other_platform_oauth_client": []
        },
        "ads_service": {
          "status": 2
        }
      }
    }
  ],
  "configuration_version": "1"
}